flask_statsdclient/__init__.py
flask_statsdclient/extension.py
Flask_StatsDClient-2.1.1.dist-info/LICENSE.md
Flask_StatsDClient-2.1.1.dist-info/METADATA
Flask_StatsDClient-2.1.1.dist-info/WHEEL
Flask_StatsDClient-2.1.1.dist-info/top_level.txt
Flask_StatsDClient-2.1.1.dist-info/RECORD
